utils/__init__.py
utils/scraperagent.py
yelphelp/__init__.py
yelphelp/yelphelp.py
yelphelp-1.0.6.dist-info/LICENSE
yelphelp-1.0.6.dist-info/METADATA
yelphelp-1.0.6.dist-info/WHEEL
yelphelp-1.0.6.dist-info/top_level.txt
yelphelp-1.0.6.dist-info/RECORD
