Metadata-Version: 2.1
Name: yelphelp
Version: 1.0.6
Summary: A small scraping tool for Yelp
Home-page: https://github.com/noahmott/yelphelp
Author: Noah Mott
Author-email: noah.mott1@gmail.com
License: Apache License 2.0
License-File: LICENSE
Requires-Dist: numpy
Requires-Dist: pandas
Requires-Dist: requests
Requires-Dist: beautifulsoup4
Requires-Dist: regex
